mysc-3.2.1.dist-info/licenses/LICENSE
myscrcpy/__init__.py
myscrcpy/run.py
myscrcpy/core/__init__.py
myscrcpy/core/adapter_cls.py
myscrcpy/core/args_cls.py
myscrcpy/core/audio.py
myscrcpy/core/connection.py
myscrcpy/core/control.py
myscrcpy/core/device.py
myscrcpy/core/extension.py
myscrcpy/core/session.py
myscrcpy/core/video.py
myscrcpy/extensions/__init__.py
myscrcpy/extensions/capture/__init__.py
myscrcpy/extensions/capture/capture.py
myscrcpy/extensions/capture/cpm.py
myscrcpy/extensions/capture/extension.toml
myscrcpy/extensions/virtualcam/__init__.py
myscrcpy/extensions/virtualcam/extension.toml
myscrcpy/extensions/virtualcam/transform.py
myscrcpy/extensions/virtualcam/virtualcam.py
myscrcpy/gui/__init__.py
myscrcpy/gui/gui_utils.py
myscrcpy/gui/dpg/__init__.py
myscrcpy/gui/dpg/dpg_extension.py
myscrcpy/gui/dpg/dpg_extension_cls.py
myscrcpy/gui/dpg/indicator.py
myscrcpy/gui/dpg/keyboard_handler.py
myscrcpy/gui/dpg/mouse_handler.py
myscrcpy/gui/dpg/video_controller.py
myscrcpy/gui/dpg/window.py
myscrcpy/gui/dpg/window_mask.py
myscrcpy/gui/dpg/components/__init__.py
myscrcpy/gui/dpg/components/component_cls.py
myscrcpy/gui/dpg/components/device.py
myscrcpy/gui/dpg/components/pad.py
myscrcpy/gui/dpg/components/scrcpy_cfg.py
myscrcpy/gui/dpg/components/vc.py
myscrcpy/gui/k/__init__.py
myscrcpy/gui/k/main.py
myscrcpy/gui/k/components/__init__.py
myscrcpy/gui/k/components/bottom_bar.py
myscrcpy/gui/k/components/connect_manager.py
myscrcpy/gui/k/components/device_panel.py
myscrcpy/gui/k/components/indicator.py
myscrcpy/gui/k/components/side_panel.py
myscrcpy/gui/k/components/video_screen.py
myscrcpy/gui/k/handler/__init__.py
myscrcpy/gui/k/handler/device_handler.py
myscrcpy/gui/k/handler/keyboard_handler.py
myscrcpy/gui/k/handler/mouse_handler.py
myscrcpy/gui/ng/__init__.py
myscrcpy/gui/ng/key_mapper.py
myscrcpy/gui/ng/main.py
myscrcpy/gui/pg/__init__.py
myscrcpy/gui/pg/game_pad.py
myscrcpy/gui/pg/tp_adapter.py
myscrcpy/gui/pg/video_controller.py
myscrcpy/gui/pg/window_control.py
mysc-3.2.1.dist-info/METADATA
mysc-3.2.1.dist-info/WHEEL
mysc-3.2.1.dist-info/entry_points.txt
mysc-3.2.1.dist-info/top_level.txt
mysc-3.2.1.dist-info/RECORD
