Metadata-Version: 2.4
Name: mysc
Version: 3.2.1
Summary: A Scrcpy client implemented in Python. Gui with Kivy/dearpygui/pygame. With Video, Audio, also Control. GUI Supports Key Proxy, Extensions, window position record, right-click gesture control, File Manager, Virtual Camera, UHID Keyboard and Chinese input and more.
Author-email: Me2sY <me2sy@outlook.com>
Project-URL: Homepage, https://github.com/me2sy/MYScrcpy
Project-URL: Issues, https://github.com/me2sy/MYScrcpy/issues
Keywords: scrcpy,android,adbutils,av,numpy,Kivy,KivyMD,DearPyGui,Pygame,adb,pyaudio
Classifier: Programming Language :: Python :: 3
Classifier: Development Status :: 4 - Beta
Classifier: License :: OSI Approved :: MIT License
Classifier: Natural Language :: Chinese (Simplified)
Classifier: Topic :: Multimedia :: Graphics :: Capture :: Screen Capture
Requires-Python: >=3.11
License-File: LICENSE
Requires-Dist: loguru
Requires-Dist: adbutils>=2.8.10
Requires-Dist: click
Requires-Dist: uiautomator2
Requires-Dist: av
Requires-Dist: numpy
Requires-Dist: pyaudio
Requires-Dist: pyperclip
Provides-Extra: gui
Requires-Dist: kivy>=2.3.1; extra == "gui"
Requires-Dist: pynput; extra == "gui"
Requires-Dist: dearpygui>=2.0.0; extra == "gui"
Requires-Dist: pygame; extra == "gui"
Requires-Dist: moosegesture; extra == "gui"
Requires-Dist: pyvirtualcam; extra == "gui"
Provides-Extra: web
Requires-Dist: nicegui; extra == "web"
Provides-Extra: flac
Requires-Dist: pyflac; extra == "flac"
Provides-Extra: opus
Requires-Dist: pyogg; extra == "opus"
Requires-Dist: opuslib; extra == "opus"
Provides-Extra: tools
Requires-Dist: pyvirtualcam; extra == "tools"
Provides-Extra: full
Requires-Dist: kivy>=2.3.1; extra == "full"
Requires-Dist: dearpygui>=2.0.0; extra == "full"
Requires-Dist: pygame; extra == "full"
Requires-Dist: pyperclip; extra == "full"
Requires-Dist: moosegesture; extra == "full"
Requires-Dist: pyvirtualcam; extra == "full"
Requires-Dist: opencv-python; extra == "full"
Requires-Dist: nicegui; extra == "full"
Requires-Dist: pyflac; extra == "full"
Requires-Dist: pyogg; extra == "full"
Requires-Dist: opuslib; extra == "full"
Dynamic: license-file
